django_utz/__init__.py
django_utz/apps.py
django_utz/config_factories.py
django_utz/datetime.py
django_utz/exceptions.py
django_utz/middleware.py
django_utz/mixins.py
django_utz/serializer_fields.py
django_utz/signals.py
django_utz/utils.py
django_utz/decorators/__init__.py
django_utz/decorators/models.py
django_utz/decorators/serializers.py
django_utz/templatetags/__init__.py
django_utz/templatetags/django_utz.py
django_utz-0.3.1.dist-info/LICENSE
django_utz-0.3.1.dist-info/METADATA
django_utz-0.3.1.dist-info/WHEEL
django_utz-0.3.1.dist-info/top_level.txt
django_utz-0.3.1.dist-info/RECORD
