Metadata-Version: 2.1
Name: django-utz
Version: 0.3.1
Summary: Get datetime values in model instances and model serializers in user's time zone without the need to manually perform timezone conversions for each user.
Author-email: "Daniel T. Afolayan (ti-oluwa)" <tioluwa.dev@gmail.com>
Maintainer-email: "Daniel T. Afolayan (ti-oluwa)" <tioluwa.dev@gmail.com>
Project-URL: Homepage, https://github.com/ti-oluwa/django_utz
Project-URL: Bug Tracker, https://github.com/ti-oluwa/django_utz/issues
Project-URL: Repository, https://github.com/ti-oluwa/django_utz
Keywords: User Timezone,Auto Timezone Conversion,Django Timezone
Classifier: Programming Language :: Python :: 3
Classifier: License :: OSI Approved :: MIT License
Classifier: Operating System :: OS Independent
Classifier: Development Status :: 4 - Beta
Classifier: Environment :: Console
Classifier: Environment :: Web Environment
Classifier: Framework :: Django
Classifier: Topic :: Software Development :: Libraries :: Python Modules
Classifier: Intended Audience :: Developers
Classifier: Natural Language :: English
Classifier: Typing :: Typed
Requires-Python: >=3.7
License-File: LICENSE
Requires-Dist: django >=3.2.5
Requires-Dist: pytz
Requires-Dist: djangorestframework
